README.md
setup.py
maradoner/__init__.py
maradoner/create.py
maradoner/dataset_filter.py
maradoner/drist.py
maradoner/export.py
maradoner/fit.py
maradoner/grn.py
maradoner/main.py
maradoner/mara.py
maradoner/meta_optimizer.py
maradoner/promoter_mean_test.py
maradoner/select.py
maradoner/synthetic_data.py
maradoner/utils.py
maradoner.egg-info/PKG-INFO
maradoner.egg-info/SOURCES.txt
maradoner.egg-info/dependency_links.txt
maradoner.egg-info/entry_points.txt
maradoner.egg-info/requires.txt
maradoner.egg-info/top_level.txt
maradoner/mara/__init__.py
maradoner/mara/export.py
maradoner/mara/fit.py
maradoner/mara/main.py