Metadata-Version: 2.2
Name: maradoner
Version: 0.27.0
Summary: Variance-adjusted estimation of motif activities.
Home-page: https://github.com/autosome-ru/maradoner
Author: Georgy Meshcheryakov
Author-email: iam@georgy.top
Classifier: Programming Language :: Python :: 3.11
Classifier: Topic :: Scientific/Engineering
Classifier: Operating System :: OS Independent
Requires-Python: >=3.11
Requires-Dist: pip>=24.0
Requires-Dist: typer>=0.13
Requires-Dist: numpy>=2.1
Requires-Dist: jax>=0.8
Requires-Dist: jaxlib>=0.8
Requires-Dist: matplotlib>=3.5
Requires-Dist: pandas>=2.2
Requires-Dist: scipy>=1.14
Requires-Dist: statsmodels>=0.14
Requires-Dist: datatable>=1.0.0
Requires-Dist: dill>=0.3.9
Requires-Dist: rich>=12.6.0
Requires-Dist: tqdm>=4.0
Requires-Dist: scikit-learn>=1.6
Requires-Dist: tables>=3.10
Requires-Dist: sympy>=1.12
Requires-Dist: seaborn>=0.12
Requires-Dist: pygam
Dynamic: author
Dynamic: author-email
Dynamic: classifier
Dynamic: description
Dynamic: description-content-type
Dynamic: home-page
Dynamic: requires-dist
Dynamic: requires-python
Dynamic: summary
